Metadata-Version: 2.1
Name: cnn-runner
Version: 0.40
Summary: Software package for CNN run
Home-page: https://github.com/xabarov/cnn_runner
Author: Xabarov Roman
Author-email: Xabarov Roman <xabarov1985@gmail.com>
License: Copyright (c) 2018 The Python Packaging Authority        
Project-URL: Homepage, https://github.com/xabarov/cnn_runner
Classifier: Programming Language :: Python :: 3
Classifier: License :: OSI Approved :: MIT License
Classifier: Operating System :: OS Independent
Requires-Python: >=3.9
License-File: LICENSE
Requires-Dist: matplotlib (>=3.5)
Requires-Dist: matplotlib-inline (>=0.1.3)
Requires-Dist: numba (>=0.56.0)
Requires-Dist: numpy (>=1.22.4)
Requires-Dist: pandas (>=1.4.3)
Requires-Dist: scipy (>=1.9.0)
Requires-Dist: tqdm (>=4.64.0)
Requires-Dist: tqdm-stubs (>=0.2.1)
